README.md
setup.py
malware_examples/__init__.py
malware_examples.egg-info/PKG-INFO
malware_examples.egg-info/SOURCES.txt
malware_examples.egg-info/dependency_links.txt
malware_examples.egg-info/top_level.txt