Metadata-Version: 2.1
Name: malware-examples
Version: 0.0.3
Summary: a few basic examples of malware along with decryptors
Author: Abhimanyu Daripally
Author-email: abhi.cl9898@gmail.com
Classifier: Development Status :: 2 - Pre-Alpha
Classifier: Intended Audience :: Education
Classifier: Programming Language :: Python :: 3.11
Classifier: License :: OSI Approved :: MIT License
Classifier: Natural Language :: English
Classifier: Operating System :: Other OS
Requires: os
Requires: cryptography
Requires: sys
